langchain_parallel_web/__init__.py
langchain_parallel_web/chat_models.py
langchain_parallel_web/parallel_web_wrapper.py
langchain_parallel_web/py.typed
langchain_parallel_web/toolkits.py
langchain_parallel_web/tools.py
langchain_parallel_web-0.0.1a0.dist-info/LICENSE
langchain_parallel_web-0.0.1a0.dist-info/METADATA
langchain_parallel_web-0.0.1a0.dist-info/WHEEL
langchain_parallel_web-0.0.1a0.dist-info/RECORD
