Metadata-Version: 2.3
Name: langchain-parallel-web
Version: 0.0.1a0
Summary: ParallelWeb integration for LangChain
License: MIT
Keywords: langchain,parallel,web,llm,ai
Author: Sanjeev Halyal
Author-email: 1448731+sanjeevhalyal@users.noreply.github.com
Requires-Python: >=3.9,<4.0
Classifier: Development Status :: 3 - Alpha
Classifier: Intended Audience :: Developers
Classifier: License :: OSI Approved :: MIT License
Classifier: Operating System :: OS Independent
Classifier: Programming Language :: Python
Classifier: Programming Language :: Python :: 3
Classifier: Programming Language :: Python :: 3.9
Classifier: Programming Language :: Python :: 3.10
Classifier: Programming Language :: Python :: 3.11
Classifier: Programming Language :: Python :: 3.12
Classifier: Programming Language :: Python :: 3.13
Classifier: Programming Language :: Python :: 3 :: Only
Classifier: Typing :: Typed
Requires-Dist: aiohttp (>=3.12.15,<4.0.0)
Requires-Dist: langchain-core (>=0.3.15,<0.4.0)
Requires-Dist: parallel-web (>=0.1.3,<0.2.0)
Requires-Dist: pydantic (>=2.11.7,<3.0.0)
Project-URL: Homepage, https://github.com/sanjeevhalyal/langchain-parallel-web
Project-URL: Issues, https://github.com/sanjeevhalyal/langchain-parallel-web/issues
Project-URL: Repository, https://github.com/sanjeevhalyal/langchain-parallel-web
Project-URL: Release Notes, https://github.com/sanjeevhalyal/langchain-parallel-web/releases
Project-URL: Source Code, https://github.com/sanjeevhalyal/langchain-parallel-web
